gorilla2d/__init__.py
gorilla2d/version.py
gorilla2d/datasets/__init__.py
gorilla2d/datasets/_utils.py
gorilla2d/datasets/dataloader.py
gorilla2d/datasets/dataset_wrappers.py
gorilla2d/datasets/randaugment.py
gorilla2d/datasets/transforms.py
gorilla2d/datasets/cls/__init__.py
gorilla2d/datasets/cls/cifar.py
gorilla2d/datasets/da/__init__.py
gorilla2d/datasets/da/digit.py
gorilla2d/datasets/da/domainnet.py
gorilla2d/datasets/da/imagelist.py
gorilla2d/datasets/da/office31.py
gorilla2d/datasets/da/officecaltech.py
gorilla2d/datasets/da/officehome.py
gorilla2d/datasets/da/visda2017.py
gorilla2d/datasets/da/open_set/__init__.py
gorilla2d/datasets/da/open_set/openset.py
gorilla2d/datasets/da/partial_set/__init__.py
gorilla2d/datasets/da/partial_set/partialset.py
gorilla2d/datasets/ssl/__init__.py
gorilla2d/datasets/ssl/cifar.py
gorilla2d/evaluation/__init__.py
gorilla2d/evaluation/cls_evaluator.py
gorilla2d/evaluation/metric/__init__.py
gorilla2d/evaluation/metric/classification.py
gorilla2d/losses/__init__.py
gorilla2d/losses/base.py
gorilla2d/losses/mcd.py
gorilla2d/losses/mmd.py
gorilla2d/losses/utils.py
gorilla2d/nn/__init__.py
gorilla2d/nn/models/__init__.py
gorilla2d/nn/modules/__init__.py
gorilla2d/nn/modules/dann.py
gorilla2d/solver/__init__.py
gorilla2d-0.2.8.7.dist-info/METADATA
gorilla2d-0.2.8.7.dist-info/WHEEL
gorilla2d-0.2.8.7.dist-info/top_level.txt
gorilla2d-0.2.8.7.dist-info/RECORD
