Metadata-Version: 2.1
Name: gorilla2d
Version: 0.2.8.7
Summary: 2D ToolBox Package for Gorilla-Lab using PyTorch
Home-page: UNKNOWN
Author: Gorilla Authors
Author-email: eehjzhang@mail.scut.edu.cn
License: MIT
Platform: UNKNOWN
Requires-Dist: numpy
Requires-Dist: tqdm
Requires-Dist: torch (>=1.1.0)
Requires-Dist: torchvision
Requires-Dist: tensorboardX
Requires-Dist: gpustat
Requires-Dist: pyyaml
Requires-Dist: yapf
Requires-Dist: addict
Requires-Dist: termcolor
Requires-Dist: tabulate
